{
  "version": "1",
  "cognitoConfig": {
    "identityPoolName": "uwalletbe7fe4d6_identitypool_be7fe4d6",
    "allowUnauthenticatedIdentities": false,
    "resourceNameTruncated": "uwallebe7fe4d6",
    "userPoolName": "uwalletbe7fe4d6_userpool_be7fe4d6",
    "autoVerifiedAttributes": [
      "email"
    ],
    "mfaConfiguration": "OFF",
    "mfaTypes": [
      "SMS Text Message"
    ],
    "smsAuthenticationMessage": "Your authentication code is {####}",
    "smsVerificationMessage": "Your verification code is {####}",
    "emailVerificationSubject": "Your verification code",
    "emailVerificationMessage": "Your verification code is {####}",
    "defaultPasswordPolicy": false,
    "passwordPolicyMinLength": 8,
    "passwordPolicyCharacters": [],
    "requiredAttributes": [
      "email",
      "family_name",
      "given_name",
      "phone_number"
    ],
    "aliasAttributes": [],
    "userpoolClientGenerateSecret": false,
    "userpoolClientRefreshTokenValidity": 30,
    "userpoolClientWriteAttributes": [
      "email"
    ],
    "userpoolClientReadAttributes": [
      "email"
    ],
    "userpoolClientLambdaRole": "uwallebe7fe4d6_userpoolclient_lambda_role",
    "userpoolClientSetAttributes": false,
    "sharedId": "be7fe4d6",
    "resourceName": "uwalletbe7fe4d6",
    "authSelections": "identityPoolAndUserPool",
    "useDefault": "default",
    "usernameAttributes": [
      "email"
    ],
    "triggers": {
      "CustomMessage": [
        "verification-link"
      ],
      "PostConfirmation": [
        "add-to-group"
      ]
    },
    "userPoolGroupList": [],
    "serviceName": "Cognito",
    "verificationBucketName": "uwalletbe7fe4d6verificationbucket",
    "usernameCaseSensitive": false,
    "useEnabledMfas": true
  }
}